LyricLib/__init__.py
LyricLib/constants.py
LyricLib/exceptions.py
LyricLib/main.py
LyricLib/subclass.py
LyricLib-0.0.4.dist-info/LICENSE.md
LyricLib-0.0.4.dist-info/METADATA
LyricLib-0.0.4.dist-info/WHEEL
LyricLib-0.0.4.dist-info/top_level.txt
LyricLib-0.0.4.dist-info/RECORD
